pdf_tools/__init__.py
pdf_tools/tools.py
pdf_tools_v1-1.3.0.dist-info/licenses/LICENSE
pdf_tools_v1-1.3.0.dist-info/METADATA
pdf_tools_v1-1.3.0.dist-info/WHEEL
pdf_tools_v1-1.3.0.dist-info/top_level.txt
pdf_tools_v1-1.3.0.dist-info/RECORD
