Metadata-Version: 2.4
Name: pdf-tools-v1
Version: 1.3.0
Summary: A simple Python package for PDF related tools
Author-email: Sarif Mia <sarifmia.ofc@gmail.com>
License: MIT
Project-URL: Homepage, https://github.com/yourusername/pdf-tools
Project-URL: Repository, https://github.com/yourusername/pdf-tools
Project-URL: Issues, https://github.com/yourusername/pdf-tools/issues
Classifier: Development Status :: 3 - Alpha
Classifier: Intended Audience :: Developers
Classifier: License :: OSI Approved :: MIT License
Classifier: Programming Language :: Python :: 3
Classifier: Programming Language :: Python :: 3.6
Classifier: Programming Language :: Python :: 3.7
Classifier: Programming Language :: Python :: 3.8
Classifier: Programming Language :: Python :: 3.9
Classifier: Programming Language :: Python :: 3.10
Classifier: Programming Language :: Python :: 3.11
Requires-Python: >=3.6
License-File: LICENSE
Requires-Dist: PyPDF2>=3.0.0
Dynamic: license-file
